nb_query/__init__.py
nb_query/main.py
nb_query-0.1.5.dist-info/LICENSE
nb_query-0.1.5.dist-info/WHEEL
nb_query-0.1.5.dist-info/METADATA
nb_query-0.1.5.dist-info/entry_points.txt
nb_query-0.1.5.dist-info/RECORD
