Metadata-Version: 2.1
Name: nb-query
Version: 0.1.5
Summary: Python package to search in jupyter notebooks
Home-page: https://github.com/xLaszlo/nb-query
License: MIT
Author: Laszlo Sragner
Author-email: sragner@gmail.com
Requires-Python: >=3.11,<3.12
Classifier: License :: OSI Approved :: MIT License
Classifier: Programming Language :: Python :: 3
Classifier: Programming Language :: Python :: 3.11
Requires-Dist: pandas (>=2.0.3,<3.0.0)
Requires-Dist: pre-commit (>=3.3.3,<4.0.0)
Requires-Dist: typer (>=0.9.0,<0.10.0)
Project-URL: Documentation, https://nb-query.readthedocs.io
Project-URL: Repository, https://github.com/xLaszlo/nb-query
